[
  {
    "icon": "website",
    "kicker": "Website Engineering",
    "title": "Website Design and Development",
    "summary": "High-performance, conversion-aware websites built with clean architecture and long-term maintainability in mind.",
    "timeline": "Typical sprint: 3 to 6 weeks",
    "outcome": "Fast pages, stronger trust, and a site your team can scale.",
    "points": [
      "Custom UX and visual system",
      "Responsive and accessibility-first frontend",
      "Performance and SEO optimization",
      "Reusable sections for easy future updates"
    ]
  },
  {
    "icon": "system",
    "kicker": "Product Systems",
    "title": "Digital Product Systems",
    "summary": "We design connected digital systems, not isolated pages, so your growth does not break the foundation.",
    "timeline": "Typical sprint: 4 to 8 weeks",
    "outcome": "Clearer workflows, stable architecture, and fewer rebuilds.",
    "points": [
      "System-level information architecture",
      "Scalable component and module planning",
      "Technical direction for future features",
      "Structured documentation for team handoff"
    ]
  },
  {
    "icon": "consult",
    "kicker": "Technical Direction",
    "title": "Technical Consultation",
    "summary": "We help teams untangle messy codebases, improve performance, and define a practical roadmap for upgrades.",
    "timeline": "Typical sprint: 1 to 3 weeks",
    "outcome": "Lower technical debt and a clearer path to ship confidently.",
    "points": [
      "Codebase audit and risk mapping",
      "Refactor and migration strategy",
      "Performance diagnosis and quick wins",
      "Prioritized implementation roadmap"
    ]
  }
]
